phandas/__init__.py
phandas/analysis.py
phandas/backtest.py
phandas/console.py
phandas/constants.py
phandas/core.py
phandas/data.py
phandas/mcp_server.py
phandas/operators.py
phandas/panel.py
phandas/plot.py
phandas/py.typed
phandas/trader.py
phandas-0.18.1.dist-info/licenses/LICENSE
tests/__init__.py
tests/conftest.py
tests/test_analysis.py
tests/test_backtest.py
tests/test_console.py
tests/test_core.py
tests/test_data.py
tests/test_operators.py
tests/test_panel.py
phandas-0.18.1.dist-info/METADATA
phandas-0.18.1.dist-info/WHEEL
phandas-0.18.1.dist-info/entry_points.txt
phandas-0.18.1.dist-info/top_level.txt
phandas-0.18.1.dist-info/RECORD
