Metadata-Version: 2.4
Name: phandas
Version: 0.18.1
Summary: A multi-factor quantitative trading framework for cryptocurrency markets.
Home-page: https://github.com/quantbai/phandas
Author: Phantom Management
Author-email: quantbai@gmail.com
Classifier: Development Status :: 4 - Beta
Classifier: Intended Audience :: Developers
Classifier: Intended Audience :: Financial and Insurance Industry
Classifier: Intended Audience :: Science/Research
Classifier: Programming Language :: Python :: 3
Classifier: Programming Language :: Python :: 3.8
Classifier: Programming Language :: Python :: 3.9
Classifier: Programming Language :: Python :: 3.10
Classifier: Programming Language :: Python :: 3.11
Classifier: Programming Language :: Python :: 3.12
Classifier: License :: OSI Approved :: MIT License
Classifier: Operating System :: OS Independent
Classifier: Topic :: Office/Business :: Financial
Classifier: Topic :: Office/Business :: Financial :: Investment
Classifier: Topic :: Scientific/Engineering
Classifier: Topic :: Scientific/Engineering :: Information Analysis
Classifier: Topic :: Scientific/Engineering :: Mathematics
Classifier: Topic :: Software Development :: Libraries :: Python Modules
Requires-Python: >=3.8
License-File: LICENSE
Requires-Dist: numpy>=2.0.0
Requires-Dist: pandas<3.0.0,>=2.0.0
Requires-Dist: matplotlib>=3.7.0
Requires-Dist: ccxt>=4.0.0
Requires-Dist: scipy>=1.9.0
Requires-Dist: python-okx>=0.4.0
Requires-Dist: requests>=2.25.0
Requires-Dist: mcp>=0.1.0
Requires-Dist: rich>=13.0.0
Dynamic: author
Dynamic: author-email
Dynamic: classifier
Dynamic: description
Dynamic: description-content-type
Dynamic: home-page
Dynamic: license-file
Dynamic: requires-dist
Dynamic: requires-python
Dynamic: summary
